poll/__init__.py
poll/poll.py
poll/settings.py
poll/tasks.py
poll/utils.py
poll/public/css/poll.css
poll/public/css/poll_edit.css
poll/public/css/themes/lms.css
poll/public/handlebars/poll_results.handlebars
poll/public/handlebars/poll_studio.handlebars
poll/public/handlebars/survey_results.handlebars
poll/public/html/poll.html
poll/public/html/poll_edit.html
poll/public/html/survey.html
poll/public/js/poll.js
poll/public/js/poll_common.js
poll/public/js/poll_edit.js
poll/public/js/translations/ar/textjs.js
poll/public/js/translations/de_DE/textjs.js
poll/public/js/translations/en/textjs.js
poll/public/js/translations/eo/textjs.js
poll/public/js/translations/es_419/textjs.js
poll/public/js/translations/fr/textjs.js
poll/public/js/translations/fr_CA/textjs.js
poll/public/js/translations/he/textjs.js
poll/public/js/translations/hi/textjs.js
poll/public/js/translations/ja_JP/textjs.js
poll/public/js/translations/ko_KR/textjs.js
poll/public/js/translations/pl/textjs.js
poll/public/js/translations/pt_BR/textjs.js
poll/public/js/translations/ru/textjs.js
poll/public/js/translations/zh_CN/textjs.js
poll/public/js/vendor/handlebars.js
poll/translations/config.yaml
poll/translations/ar/LC_MESSAGES/text.mo
poll/translations/ar/LC_MESSAGES/text.po
poll/translations/de_DE/LC_MESSAGES/text.mo
poll/translations/de_DE/LC_MESSAGES/text.po
poll/translations/de_DE/LC_MESSAGES/textjs.po
poll/translations/en/LC_MESSAGES/text.mo
poll/translations/en/LC_MESSAGES/text.po
poll/translations/en/LC_MESSAGES/textjs.po
poll/translations/eo/LC_MESSAGES/text.mo
poll/translations/eo/LC_MESSAGES/text.po
poll/translations/eo/LC_MESSAGES/textjs.po
poll/translations/es_419/LC_MESSAGES/text.mo
poll/translations/es_419/LC_MESSAGES/text.po
poll/translations/es_419/LC_MESSAGES/textjs.po
poll/translations/fr/LC_MESSAGES/text.mo
poll/translations/fr/LC_MESSAGES/text.po
poll/translations/fr/LC_MESSAGES/textjs.po
poll/translations/fr_CA/LC_MESSAGES/text.mo
poll/translations/fr_CA/LC_MESSAGES/text.po
xblock_poll-1.14.0.dist-info/LICENSE
xblock_poll-1.14.0.dist-info/METADATA
xblock_poll-1.14.0.dist-info/WHEEL
xblock_poll-1.14.0.dist-info/entry_points.txt
xblock_poll-1.14.0.dist-info/top_level.txt
xblock_poll-1.14.0.dist-info/RECORD
