Metadata-Version: 2.1
Name: xblock-poll
Version: 1.14.0
Summary: An XBlock for polling users.
Home-page: https://github.com/open-craft/xblock-poll
Classifier: Development Status :: 5 - Production/Stable
Classifier: Intended Audience :: Education
Classifier: License :: OSI Approved :: GNU Affero General Public License v3 or later (AGPLv3+)
Classifier: Natural Language :: English
Classifier: Programming Language :: Python :: 3.8
License-File: LICENSE
Requires-Dist: bleach[css]
Requires-Dist: django-statici18n
Requires-Dist: markdown
Requires-Dist: xblock-utils
